{
  "name": "Elspec Engineering",
  "description": "They provide sophisticated power quality analyzers and meters with continuous waveform recording tailored for renewable energy applications.",
  "categoryId": 17,
  "size": "m",
  "logoFile": "logos/elspec_engineering_ltd-logo.webp",
  "websiteUrl": "https://www.elspec-ltd.com/",
  "careersUrl": "https://www.elspec-ltd.com/careers/",
  "isHiring": true,
  "linkedinId": "elspec-ltd.",
  "crunchbaseId": null,
  "finderId": "elspec-engineering",
  "xId": null,
  "addresses": [
    {
      "street": "שוהם",
      "houseNumber": 4,
      "city": "קיסריה",
      "lat": 32.4891572,
      "lon": 34.9061208
    }
  ],
  "isMultinational": false,
  "facebookId": "Elspec.Ltd",
  "linkedinNum": 511471
}