{
  "name": "Grin Mendel And Sons",
  "description": "Experience AI-driven influencer marketing and seamless payment solutions through our advanced software.",
  "categoryId": 2,
  "size": "s",
  "logoFile": "logos/grin_mendel_and_sons-logo.webp",
  "websiteUrl": "https://grin.co/",
  "careersUrl": "https://grin.co/careers/",
  "isHiring": true,
  "linkedinId": null,
  "crunchbaseId": null,
  "finderId": "grin",
  "xId": null,
  "addresses": [
    {
      "street": "האורג",
      "houseNumber": 23,
      "city": "נתניה",
      "lat": 32.3188664,
      "lon": 34.8717241
    }
  ]
}