{
  "name": "MedSim",
  "description": "The UltraSim® Ultrasound Simulator offers realistic, hands-on training for medical students and professionals, widely preferred by over 1,250 global customers.",
  "categoryId": 12,
  "size": "s",
  "logoFile": "logos/medsim-logo.webp",
  "websiteUrl": "https://medsim.com/",
  "careersUrl": null,
  "linkedinId": "medsim",
  "linkedinNum": 93330,
  "crunchbaseId": null,
  "ivcId": null,
  "finderId": "medsim",
  "xId": null,
  "facebookId": "UltrasoundSimulation",
  "breezyId": null,
  "comeetId": null,
  "greenhouseId": null,
  "leverId": null,
  "addresses": [
    {
      "street": "היצירה",
      "houseNumber": 10,
      "city": "רעננה",
      "lat": 32.1950061,
      "lon": 34.8768325
    }
  ],
  "isMultinational": false,
  "isActive": true
}