{
  "name": "Sol Gel Technologies",
  "description": "Developing cutting-edge treatments for rare skin conditions, we collaborate to advance dermatological care.",
  "categoryId": 12,
  "size": "m",
  "logoFile": "logos/sol_gel_technologies-logo.webp",
  "websiteUrl": "https://www.sol-gel.com/",
  "careersUrl": null,
  "isHiring": false,
  "linkedinId": null,
  "crunchbaseId": null,
  "finderId": "sol-gel",
  "xId": null,
  "addresses": [
    {
      "street": "גולדה מאיר",
      "houseNumber": 7,
      "city": "נס ציונה",
      "lat": 31.9160002,
      "lon": 34.8020721
    }
  ]
}