{
  "name": "888",
  "description": "888 Holdings plc (and together with its subsidiaries, \"888\" or the \"Group\") is one of the world's leading betting and gaming companies.",
  "categoryId": 14,
  "size": "xl",
  "logoFile": "logos/888-logo.webp",
  "websiteUrl": "http://www.888holdingsplc.com",
  "careersUrl": "https://www.evokeplc.com/careers/",
  "linkedinId": "888.com",
  "linkedinNum": 7349,
  "crunchbaseId": null,
  "ivcId": "A1000000003311",
  "finderId": null,
  "xId": null,
  "facebookId": null,
  "breezyId": null,
  "comeetId": null,
  "greenhouseId": null,
  "leverId": null,
  "addresses": [
    {
      "street": "מדינת היהודים",
      "houseNumber": 85,
      "city": "הרצליה",
      "lat": 32.1666328,
      "lon": 34.8100707
    }
  ],
  "isMultinational": false,
  "isActive": true
}