{
  "name": "SerVision",
  "description": "We lead in safety innovation, offering advanced technologies for vehicles of all types to ensure accessible and dependable protection for every journey.",
  "categoryId": 7,
  "size": "s",
  "logoFile": "logos/servision-logo.webp",
  "websiteUrl": "https://servision.net/",
  "careersUrl": null,
  "linkedinId": "servision-inc",
  "linkedinNum": 4744334,
  "crunchbaseId": null,
  "ivcId": null,
  "finderId": "servision",
  "xId": "SerVisionLtd",
  "facebookId": "servision",
  "breezyId": null,
  "comeetId": null,
  "greenhouseId": null,
  "leverId": null,
  "addresses": [
    {
      "street": "איתן",
      "houseNumber": 1,
      "city": "ראשון לציון",
      "lat": 31.99353945,
      "lon": 34.76535052179885
    }
  ],
  "isMultinational": false,
  "isActive": true
}