{
  "name": "Inomize",
  "description": "Expert in ASIC design and hardware solutions, specializing in advanced FinFET, mixed signal, analog, RF, BCD, and high voltage technologies for OEMs and ODMs.",
  "categoryId": 16,
  "size": "s",
  "logoFile": "logos/inomize-logo.webp",
  "websiteUrl": "https://www.verisense.co.il/",
  "careersUrl": null,
  "isHiring": false,
  "linkedinId": "inomize",
  "crunchbaseId": null,
  "finderId": "inomize",
  "xId": null,
  "addresses": [
    {
      "street": "עמק זבולון",
      "houseNumber": 12,
      "city": "כפר סבא",
      "lat": 32.1812856,
      "lon": 34.9333691
    }
  ]
}