{
  "name": "NRGene",
  "description": "Leveraging genomic data and AI, this company swiftly identifies optimal solutions for sustainability.",
  "categoryId": 1,
  "size": "s",
  "logoFile": "logos/nrgene_technologies-logo.webp",
  "websiteUrl": "https://nrgene.com/",
  "careersUrl": "https://nrgene.com/careers/",
  "linkedinId": "nrgene-ltd",
  "linkedinNum": 1704972,
  "crunchbaseId": null,
  "ivcId": "A1000000009771",
  "finderId": "nrgene",
  "xId": "NRGene",
  "facebookId": "NRGene-Technologies-1003279819696574",
  "breezyId": null,
  "comeetId": null,
  "greenhouseId": null,
  "leverId": null,
  "addresses": [
    {
      "street": "גולדה מאיר",
      "houseNumber": 5,
      "city": "נס ציונה",
      "lat": 31.9160002,
      "lon": 34.8020721
    }
  ],
  "isMultinational": false,
  "isActive": true
}