{
  "name": "Renalsense",
  "description": "An experienced entrepreneur with a deep background in the renal and critical care industry, known for transforming start-ups into global medical device providers.",
  "categoryId": 12,
  "size": "s",
  "logoFile": "logos/renalsense-logo.webp",
  "websiteUrl": "https://www.renalsense.com/",
  "careersUrl": null,
  "isHiring": false,
  "linkedinId": "renalsense",
  "crunchbaseId": null,
  "finderId": "renalsense",
  "xId": null,
  "addresses": [
    {
      "street": "המרפא",
      "houseNumber": 3,
      "city": "ירושלים",
      "lat": 31.8011374,
      "lon": 35.21198
    }
  ]
}