{
  "name": "Sight Diagnostics",
  "description": "Sight Diagnostics developed blood diagnostic products, based on computer vision and artificial intelligence.",
  "categoryId": 12,
  "size": "m",
  "logoFile": "logos/sight-diagnostics-logo.webp",
  "websiteUrl": "https://sightdx.com/en-us",
  "careersUrl": "https://sightdx.com/en-us/careers",
  "linkedinId": "sight-diagnostics",
  "linkedinNum": 5066984,
  "crunchbaseId": null,
  "ivcId": "A1000000021191",
  "finderId": null,
  "xId": null,
  "facebookId": null,
  "breezyId": null,
  "comeetId": null,
  "greenhouseId": null,
  "leverId": null,
  "addresses": [
    {
      "street": "מנחם בגין",
      "houseNumber": 23,
      "city": "בני ברק",
      "lat": 32.0929164,
      "lon": 34.8295488
    }
  ],
  "isMultinational": false,
  "isActive": true
}