{
  "name": "Pink Park",
  "description": "Transforming parking with a smart app for reserving, navigating, and paying for eco-friendly urban spots.",
  "categoryId": 9,
  "size": "xs",
  "logoFile": "logos/pink_park-logo.webp",
  "websiteUrl": "https://pinkpark.co.il/",
  "careersUrl": null,
  "linkedinId": null,
  "linkedinNum": 6356270,
  "crunchbaseId": null,
  "ivcId": null,
  "finderId": "pinkpark",
  "xId": null,
  "facebookId": "pinkparking",
  "breezyId": null,
  "comeetId": null,
  "greenhouseId": null,
  "leverId": null,
  "addresses": [
    {
      "street": "המפלסים",
      "houseNumber": 17,
      "city": "פתח תקווה",
      "lat": 32.1015806,
      "lon": 34.8635276
    }
  ],
  "isMultinational": false,
  "isActive": true
}