{
  "name": "Safer Place",
  "description": "Safer Place enables police and municipalities to streamline traffic enforcement operations, increase road safety and compliance, drive productivity and ...",
  "categoryId": 7,
  "size": "s",
  "logoFile": "logos/safer_place-logo.webp",
  "websiteUrl": "https://saferplace.com/",
  "careersUrl": null,
  "linkedinId": "safer-place-ltd-",
  "linkedinNum": 10283102,
  "crunchbaseId": null,
  "ivcId": "A1000000021526",
  "finderId": "safer-place",
  "xId": null,
  "facebookId": null,
  "breezyId": null,
  "comeetId": null,
  "greenhouseId": null,
  "leverId": null,
  "addresses": [
    {
      "street": "אמיר גלבוע",
      "houseNumber": 5,
      "city": "תל אביב-יפו",
      "lat": 32.1173598,
      "lon": 34.787493
    }
  ],
  "isMultinational": false,
  "isActive": true
}