{
  "name": "Re Sec Technologies",
  "description": "Document Security with Zero Trust Principles.",
  "categoryId": 7,
  "size": "s",
  "logoFile": "logos/re_sec_technologies-logo.webp",
  "websiteUrl": "https://resec.co/",
  "careersUrl": "https://resec.co/careers/",
  "isHiring": true,
  "linkedinId": "re-sec-technologies-ltd",
  "crunchbaseId": "re-sec-technologies",
  "finderId": "re-sec-technologies",
  "xId": null,
  "addresses": [
    {
      "street": "הטוחן",
      "houseNumber": 2,
      "city": "קיסריה",
      "lat": 32.4863102,
      "lon": 34.9521262
    }
  ]
}