{
  "name": "ChessMatec",
  "description": "ChessMatec app is a fun, interactive educational platform, which teaches life skills through the game of chess.",
  "categoryId": 8,
  "size": "xs",
  "logoFile": "logos/chessmatec-logo.webp",
  "websiteUrl": "https://www.chessmatec.com",
  "careersUrl": null,
  "linkedinId": "chessmatec",
  "linkedinNum": 35480421,
  "crunchbaseId": null,
  "ivcId": "A1000000416814",
  "finderId": null,
  "xId": null,
  "facebookId": null,
  "breezyId": null,
  "comeetId": null,
  "greenhouseId": null,
  "leverId": null,
  "addresses": [
    {
      "street": "הבשן",
      "houseNumber": 18,
      "city": "ראשון לציון",
      "lat": 31.9590696,
      "lon": 34.7935594
    }
  ],
  "isMultinational": false,
  "isActive": true
}