{
  "name": "Bit2c",
  "description": "Bit2C offers services, such as secure custody for digital assets and custody of money; a trading platform (exchange) for managing advanced trading in digital assets; an online broker and OTC desk that allows immediate buying and selling of digital currencies.",
  "categoryId": 9,
  "size": "xs",
  "logoFile": "logos/bit2c-logo.webp",
  "websiteUrl": "http://www.bit2c.co.il",
  "careersUrl": null,
  "linkedinId": "bit2c",
  "linkedinNum": 4998867,
  "crunchbaseId": null,
  "ivcId": "A1000000023559",
  "finderId": null,
  "xId": null,
  "facebookId": null,
  "breezyId": null,
  "comeetId": null,
  "greenhouseId": null,
  "leverId": null,
  "addresses": [
    {
      "street": "הכישור",
      "houseNumber": 30,
      "city": "חולון",
      "lat": 32.0040079,
      "lon": 34.8022417
    }
  ],
  "isMultinational": false,
  "isActive": true
}