{
  "name": "Adit-Media",
  "description": "Adit-Media is an online performance-based ad network that provides ROI for advertisers and publishers.",
  "categoryId": 8,
  "size": "xs",
  "logoFile": "logos/adit-media-logo.webp",
  "websiteUrl": "http://adit-media.com/",
  "careersUrl": null,
  "linkedinId": "adit-media",
  "linkedinNum": 3658036,
  "crunchbaseId": null,
  "ivcId": "A1000000201587",
  "finderId": null,
  "xId": null,
  "facebookId": null,
  "breezyId": null,
  "comeetId": null,
  "greenhouseId": null,
  "leverId": null,
  "addresses": [
    {
      "street": "שדרות רוטשילד",
      "houseNumber": 73,
      "city": "תל אביב-יפו",
      "lat": 32.0658091,
      "lon": 34.7769461
    }
  ],
  "isMultinational": false,
  "isActive": true
}