{
  "name": "BreatheVision",
  "description": "We provide wearable sensors and AI technology to continuously monitor and alert healthcare teams about patients' breathing to prevent respiratory emergencies.",
  "categoryId": 12,
  "size": "xs",
  "logoFile": "logos/breathevision-logo.webp",
  "websiteUrl": "https://breathevision.com/",
  "careersUrl": null,
  "linkedinId": "breathevision",
  "linkedinNum": 10356498,
  "crunchbaseId": null,
  "ivcId": "A1000000191284",
  "finderId": "breathevision",
  "xId": null,
  "facebookId": "pages",
  "breezyId": null,
  "comeetId": null,
  "greenhouseId": null,
  "leverId": null,
  "addresses": [
    {
      "street": "החרש",
      "houseNumber": 6,
      "city": "נס ציונה",
      "lat": 31.9224308,
      "lon": 34.7997361
    }
  ],
  "isMultinational": false,
  "isActive": true
}