{
  "name": "Milkit Israel",
  "description": "Offering innovative solutions for simplified tubeless tire installation and sealant management.",
  "categoryId": 5,
  "size": "xs",
  "logoFile": "logos/milkit_israel-logo.webp",
  "websiteUrl": "https://milkit.bike/",
  "careersUrl": null,
  "isHiring": false,
  "linkedinId": null,
  "crunchbaseId": null,
  "finderId": "milkit-ltd",
  "xId": null,
  "addresses": [
    {
      "street": "ויצמן",
      "houseNumber": 4,
      "city": "תל אביב - יפו",
      "lat": 32.0782941,
      "lon": 34.7886936
    }
  ]
}