{
  "name": "Roundforest",
  "description": "Empowering online shoppers with advanced tools for informed purchasing decisions, facilitating $1B in annual sales.",
  "categoryId": 9,
  "size": "s",
  "logoFile": "logos/roundforest-logo.webp",
  "websiteUrl": "https://www.roundforest.com/",
  "careersUrl": null,
  "isHiring": false,
  "linkedinId": "roundforest",
  "crunchbaseId": null,
  "finderId": "roundforest",
  "xId": null,
  "addresses": [
    {
      "street": "אלון יגאל",
      "houseNumber": 94,
      "city": "תל אביב - יפו",
      "lat": 32.0687595,
      "lon": 34.7939327
    }
  ],
  "isMultinational": false,
  "facebookId": "pages",
  "linkedinNum": 5214030
}