{
  "name": "EchoCare Technologies",
  "description": "Noninvasive Home Monitoring System for Seniors",
  "categoryId": 12,
  "size": "s",
  "logoFile": "logos/echocare_technologies-logo.webp",
  "websiteUrl": "https://www.echocare-tech.com/",
  "careersUrl": null,
  "isHiring": false,
  "linkedinId": "echocare-technologies",
  "crunchbaseId": null,
  "finderId": "echocare",
  "xId": null,
  "addresses": [
    {
      "street": "גולדה מאיר",
      "houseNumber": 5,
      "city": "נס ציונה",
      "lat": 31.9137859,
      "lon": 34.8024773
    }
  ],
  "isMultinational": false,
  "linkedinNum": 9349377
}
