{
  "name": "Xeye",
  "description": "Xeye.ai redefines the future of crowd security by scanning for concealed items among many people at a distance with completely touchless, non-invasive, and safe technology.",
  "categoryId": 7,
  "size": "xs",
  "logoFile": "logos/xeye-logo.webp",
  "websiteUrl": "https://xeye.ai",
  "careersUrl": null,
  "linkedinId": "x-eye",
  "linkedinNum": 27032719,
  "crunchbaseId": null,
  "ivcId": "A1000000281429",
  "finderId": null,
  "xId": null,
  "facebookId": null,
  "breezyId": null,
  "comeetId": null,
  "greenhouseId": null,
  "leverId": null,
  "addresses": [
    {
      "street": "שופמן",
      "houseNumber": 9,
      "city": "חיפה",
      "lat": 32.7662124,
      "lon": 34.98428639999999
    }
  ],
  "isMultinational": false,
  "isActive": true
}