{
  "name": "Libra@Home",
  "description": "Libra@Home has developed a fully immersive virtual reality tool for physical and occupational therapists to improve the delivery and quality of treatment to patients with neurological disorders, both in the clinic and at home.",
  "categoryId": 12,
  "size": "xs",
  "logoFile": "logos/libra_home-logo.webp",
  "websiteUrl": "https://librahome.com",
  "careersUrl": null,
  "linkedinId": "libra-home",
  "linkedinNum": null,
  "crunchbaseId": null,
  "ivcId": "A1000000169623",
  "finderId": null,
  "xId": null,
  "facebookId": null,
  "breezyId": null,
  "comeetId": null,
  "greenhouseId": null,
  "leverId": null,
  "addresses": [
    {
      "street": "אביר יעקב",
      "houseNumber": 26,
      "city": "ירושלים",
      "lat": 31.839558,
      "lon": 35.24933800000001
    }
  ],
  "isMultinational": false,
  "isActive": true
}