{
  "name": "Metis",
  "description": "Always Optimized No-Ops Data Infrastructure at Scale",
  "categoryId": 14,
  "size": "s",
  "logoFile": "logos/metis_corp-logo.webp",
  "websiteUrl": "https://www.metisdata.io/",
  "careersUrl": null,
  "isHiring": false,
  "linkedinId": null,
  "crunchbaseId": null,
  "finderId": "metis",
  "xId": null,
  "addresses": [
    {
      "street": "ויינשל",
      "houseNumber": 5,
      "city": "תל אביב - יפו",
      "lat": 32.117498,
      "lon": 34.82264
    }
  ],
  "isMultinational": false,
  "linkedinNum": 75050116
}