{
  "name": "Rayven IOT",
  "description": "Specializing in ultra-interoperable middleware, they provide seamless integration of data and systems for creating real-time industrial technology ecosystems.",
  "categoryId": 13,
  "size": "s",
  "logoFile": "logos/rayven_iot-logo.webp",
  "websiteUrl": "https://www.rayven.io/",
  "careersUrl": null,
  "linkedinId": null,
  "linkedinNum": 12176697,
  "crunchbaseId": null,
  "ivcId": null,
  "finderId": "rayven-iot",
  "xId": "rayveniot",
  "facebookId": null,
  "breezyId": null,
  "comeetId": null,
  "greenhouseId": null,
  "leverId": null,
  "addresses": [
    {
      "street": "קרן היסוד",
      "houseNumber": 2,
      "city": "רעננה",
      "lat": 32.1859632,
      "lon": 34.8716408
    }
  ],
  "isMultinational": false,
  "isActive": true
}