{
  "name": "Neuroindex",
  "description": "Founded by Dr. Shimon Eckhouse, this early-stage VC firm funds innovative medical device startups to enhance global well-being and quality of life.",
  "categoryId": 12,
  "size": "xs",
  "logoFile": "logos/neuroindex-logo.webp",
  "websiteUrl": "https://alon-medtech.com/",
  "careersUrl": null,
  "linkedinId": null,
  "linkedinNum": null,
  "crunchbaseId": null,
  "ivcId": null,
  "finderId": "neuroindex",
  "xId": null,
  "facebookId": null,
  "breezyId": null,
  "comeetId": null,
  "greenhouseId": null,
  "leverId": null,
  "addresses": [
    {
      "street": "בית תבור 2",
      "houseNumber": null,
      "city": "יקנעם עילית",
      "lat": 32.665530818580166,
      "lon": 35.10411800897265
    }
  ],
  "isMultinational": false,
  "isActive": true
}