{
  "name": "Prosper3D",
  "description": "Custom Software Development for 3D Printing",
  "categoryId": 14,
  "size": "xs",
  "logoFile": "logos/prosper_3_d-logo.webp",
  "websiteUrl": "https://www.prosper3d.com",
  "careersUrl": null,
  "linkedinId": "prosper3d",
  "linkedinNum": 17882396,
  "crunchbaseId": null,
  "ivcId": null,
  "finderId": "prosper3d",
  "xId": "prosper3d",
  "facebookId": "prosper3d",
  "breezyId": null,
  "comeetId": null,
  "greenhouseId": null,
  "leverId": null,
  "addresses": [
    {
      "street": "אלון יגאל",
      "houseNumber": 116,
      "city": "תל אביב-יפו",
      "lat": 32.073165,
      "lon": 34.795106
    }
  ],
  "isMultinational": false,
  "isActive": true
}