{
  "name": "Fortephest",
  "description": "Established in 2017, this biotech firm specializes in developing innovative, plant-inspired solutions for effective and resistant weed control in crops.",
  "categoryId": 12,
  "size": "xs",
  "logoFile": "logos/fortephest-logo.webp",
  "websiteUrl": "http://fortephest.com/",
  "careersUrl": null,
  "isHiring": false,
  "linkedinId": null,
  "crunchbaseId": null,
  "finderId": "fortephest",
  "xId": null,
  "addresses": [
    {
      "street": "דן",
      "houseNumber": 3,
      "city": "נס ציונה",
      "lat": 31.9289715,
      "lon": 34.7882439
    }
  ]
}