{
  "name": "Curesponse",
  "description": "Their innovative 3D tissue culture system models cancer growth and drug response by preserving the tissue's original architecture.",
  "categoryId": 12,
  "size": "s",
  "logoFile": "logos/curesponse-logo.webp",
  "websiteUrl": "https://www.curesponse.com/",
  "careersUrl": null,
  "linkedinId": "curesponse",
  "linkedinNum": 18434992,
  "crunchbaseId": null,
  "ivcId": "A1000000248899",
  "finderId": "curesponse",
  "xId": null,
  "facebookId": "Curesponse",
  "breezyId": null,
  "comeetId": null,
  "greenhouseId": null,
  "leverId": null,
  "addresses": [
    {
      "street": "אופנהיימר",
      "houseNumber": 2,
      "city": "תל אביב-יפו",
      "lat": 32.1185525,
      "lon": 34.8004103
    }
  ],
  "isMultinational": false,
  "isActive": true
}