{
  "name": "InnoCan Pharma",
  "description": "A specialty pharma innovator focused on cannabinoid-based products with proprietary delivery technologies and exclusive commercialization rights.",
  "categoryId": 12,
  "size": "s",
  "logoFile": "logos/innocan_pharma-logo.webp",
  "websiteUrl": "https://innocanpharma.com/",
  "careersUrl": null,
  "isHiring": false,
  "linkedinId": "innocanpharma",
  "crunchbaseId": null,
  "finderId": "innocan-pharma",
  "xId": "innocanp",
  "addresses": [
    {
      "street": "אריק איינשטיין",
      "houseNumber": 3,
      "city": "הרצליה",
      "lat": 32.1630763,
      "lon": 34.8150141
    }
  ],
  "isMultinational": false,
  "facebookId": "Innocanpharma",
  "linkedinNum": 28636009
}
