{
  "name": "Arcana Instruments",
  "description": "Founded in 2015, this company unites musicians, engineers, and designers to create inclusive musical experiences for those facing difficulties.",
  "categoryId": 12,
  "size": "xs",
  "logoFile": "logos/arcana_instruments-logo.webp",
  "websiteUrl": "https://arcanainstruments.com/",
  "careersUrl": null,
  "isHiring": false,
  "linkedinId": "arcana-instruments-ltd",
  "crunchbaseId": null,
  "finderId": "arcana-instruments",
  "xId": null,
  "addresses": [
    {
      "street": "השדה",
      "houseNumber": 224,
      "city": "פרדס חנה-כרכור",
      "lat": 32.478772,
      "lon": 34.9785713
    }
  ]
}