{
  "name": "Pangea Biomed",
  "description": "The platform reveals tumor vulnerabilities by integrating functional genetic interactions with diverse biological data, constructing comprehensive gene networks for clinical insights.",
  "categoryId": 12,
  "size": "s",
  "logoFile": "logos/pangea_biomed-logo.webp",
  "websiteUrl": "https://pangeabiomed.com/",
  "careersUrl": null,
  "linkedinId": "pangea-biomed",
  "linkedinNum": 71201409,
  "crunchbaseId": null,
  "ivcId": "A1000000324044",
  "finderId": "pangea-biomed",
  "xId": "PangeaBiomed",
  "facebookId": null,
  "breezyId": null,
  "comeetId": null,
  "greenhouseId": null,
  "leverId": null,
  "addresses": [
    {
      "street": "הברזל",
      "houseNumber": 2,
      "city": "תל אביב-יפו",
      "lat": 32.106356,
      "lon": 34.834755
    }
  ],
  "isMultinational": false,
  "isActive": true
}