{
  "name": "VoicEncode",
  "description": "Speech Recognition Technology",
  "categoryId": 14,
  "size": "xs",
  "logoFile": "logos/voicencode-logo.webp",
  "websiteUrl": "https://voicencode.com/",
  "careersUrl": null,
  "isHiring": false,
  "linkedinId": "voicencode",
  "crunchbaseId": "voicencode",
  "finderId": "voicencode",
  "xId": null,
  "addresses": [
    {
      "street": "עפרוני",
      "houseNumber": 8,
      "city": "כפר סבא",
      "lat": 32.1848844,
      "lon": 34.928684
    }
  ],
  "isMultinational": false,
  "linkedinNum": 11519127
}