{
  "name": "SpeedSize",
  "description": "Media Compression Powered by AI.",
  "categoryId": 1,
  "size": "s",
  "logoFile": "logos/speedsize-logo.webp",
  "websiteUrl": "https://speedsize.com/",
  "careersUrl": null,
  "linkedinId": "speedsize",
  "linkedinNum": 42424479,
  "crunchbaseId": "speedsize",
  "ivcId": "A1000000308569",
  "finderId": "speedsize",
  "xId": null,
  "facebookId": "SpeedSize-112114417154876",
  "breezyId": null,
  "comeetId": null,
  "greenhouseId": null,
  "leverId": null,
  "addresses": [
    {
      "street": null,
      "houseNumber": null,
      "city": "נתניה",
      "lat": 32.321458,
      "lon": 34.853196
    }
  ],
  "isMultinational": false,
  "isActive": true
}