{
  "name": "Tensorleap",
  "description": "A platform enhancing the development of Deep Neural Networks by offering advanced debugging, observability, and explainability tools for data scientists.",
  "categoryId": 1,
  "size": "s",
  "logoFile": "logos/tensorleap-logo.webp",
  "websiteUrl": "https://docs.tensorleap.ai/",
  "careersUrl": null,
  "isHiring": false,
  "linkedinId": null,
  "crunchbaseId": null,
  "finderId": "tensorleap",
  "xId": null,
  "addresses": [
    {
      "street": "תובל",
      "houseNumber": 40,
      "city": "רמת גן",
      "lat": 32.08501775,
      "lon": 34.80164595917552
    }
  ]
}