{
  "name": "Teracyte Analytics",
  "description": "Integrating high-throughput flow cytometry with live-cell microscopy, this company revolutionizes cellular analysis by enabling profound insights from complex datasets.",
  "categoryId": 12,
  "size": "xs",
  "logoFile": "logos/teracyte_analytics-logo.webp",
  "websiteUrl": "https://www.teracyte.ai/",
  "careersUrl": null,
  "isHiring": false,
  "linkedinId": null,
  "crunchbaseId": null,
  "finderId": "teracyte-analytics",
  "xId": null,
  "addresses": [
    {
      "street": "הטוחן",
      "houseNumber": 17,
      "city": "קיסריה",
      "lat": 32.4857297,
      "lon": 34.9462968
    }
  ]
}