{
  "name": "Tera-Pass",
  "description": "Processors for Optical Transport Networks in Mobile Services.",
  "categoryId": 16,
  "size": "xs",
  "logoFile": "logos/tera_pass-logo.webp",
  "websiteUrl": "https://www.tera-pass.com/",
  "careersUrl": null,
  "linkedinId": "ip-light",
  "linkedinNum": 1035345,
  "crunchbaseId": null,
  "ivcId": "A1000000002331",
  "finderId": "ip-light",
  "xId": null,
  "facebookId": null,
  "breezyId": null,
  "comeetId": null,
  "greenhouseId": null,
  "leverId": null,
  "addresses": [
    {
      "street": "4",
      "houseNumber": null,
      "city": "פתח תקווה",
      "lat": 32.104883,
      "lon": 34.848894
    }
  ],
  "isMultinational": false,
  "isActive": true
}