{
  "name": "LittleOne.Care",
  "description": "A top-rated 2023 baby monitor using AI to deliver 24/7 real-time alerts and parenting tips for your child's safety and happiness.",
  "categoryId": 12,
  "size": "xs",
  "logoFile": "logos/littleone_care-logo.webp",
  "websiteUrl": "https://www.littleone.care/",
  "careersUrl": null,
  "linkedinId": "littleonecare",
  "linkedinNum": 20555634,
  "crunchbaseId": null,
  "ivcId": "A1000000311975",
  "finderId": "littleone-care",
  "xId": "littleonecare",
  "facebookId": "little1care",
  "breezyId": null,
  "comeetId": null,
  "greenhouseId": null,
  "leverId": null,
  "addresses": [
    {
      "street": "ישראל בן ציון",
      "houseNumber": 7,
      "city": "בת ים",
      "lat": 32.0163494,
      "lon": 34.7458963
    }
  ],
  "isMultinational": false,
  "isActive": true
}