{
  "name": "Briya",
  "description": "Making healthcare data accessible and easily shareable to drive health innovation.",
  "categoryId": 12,
  "size": "s",
  "logoFile": "logos/briya_labs-logo.webp",
  "websiteUrl": "https://briya.com/",
  "careersUrl": "https://www.linkedin.com/company/briyahealth/jobs/",
  "linkedinId": "briyahealth",
  "linkedinNum": 79982772,
  "crunchbaseId": null,
  "ivcId": null,
  "finderId": "bria-interoperability",
  "xId": "BriyaHealth",
  "facebookId": "briya.health",
  "breezyId": null,
  "comeetId": null,
  "greenhouseId": null,
  "leverId": null,
  "addresses": [
    {
      "street": "שאול המלך",
      "houseNumber": 35,
      "city": "תל אביב-יפו",
      "lat": 32.0777064,
      "lon": 34.78983779282785
    }
  ],
  "isMultinational": false,
  "isActive": true
}