{
  "name": "Airtonics Health",
  "description": "In stealth mode.",
  "categoryId": 12,
  "size": "xs",
  "logoFile": "logos/airtonics_health-logo.webp",
  "websiteUrl": "https://www.airtonics.com",
  "careersUrl": null,
  "linkedinId": null,
  "linkedinNum": null,
  "crunchbaseId": null,
  "ivcId": "A1000000366894",
  "finderId": "vytonic-medical",
  "xId": null,
  "facebookId": null,
  "breezyId": null,
  "comeetId": null,
  "greenhouseId": null,
  "leverId": null,
  "addresses": [
    {
      "street": "מחנה יוסף",
      "houseNumber": 23,
      "city": "תל אביב-יפו",
      "lat": 32.0642028,
      "lon": 34.7665798
    }
  ],
  "isMultinational": false,
  "isActive": true
}