{
  "name": "babyark",
  "description": "Pioneering unparalleled child safety with cutting-edge car seat design and technology.",
  "categoryId": 5,
  "size": "s",
  "logoFile": "logos/babyark-logo.webp",
  "websiteUrl": "https://babyark.com/",
  "careersUrl": null,
  "isHiring": false,
  "linkedinId": null,
  "crunchbaseId": null,
  "finderId": "babyark",
  "xId": null,
  "addresses": [
    {
      "street": "עתירי ידע",
      "houseNumber": 17,
      "city": "כפר סבא",
      "lat": 32.1666204,
      "lon": 34.9281644
    }
  ],
  "isMultinational": false,
  "facebookId": "getbabyark",
  "linkedinNum": 70931102
}