{
  "name": "RapidoCAD",
  "description": "Leveraging AI and Big Data, this company streamlines the building permit process for architects, enhancing efficiency and reducing bureaucracy.",
  "categoryId": 1,
  "size": "xs",
  "logoFile": "logos/rapidocad-logo.webp",
  "websiteUrl": "https://rapidocad.com/",
  "careersUrl": null,
  "linkedinId": "rapidocad",
  "linkedinNum": 68229436,
  "crunchbaseId": null,
  "ivcId": "A1000000320572",
  "finderId": "rapidocad",
  "xId": null,
  "facebookId": null,
  "breezyId": null,
  "comeetId": null,
  "greenhouseId": null,
  "leverId": null,
  "addresses": [
    {
      "street": null,
      "houseNumber": null,
      "city": "ירושלים",
      "lat": 31.768319,
      "lon": 35.21371
    }
  ],
  "isMultinational": false,
  "isActive": true
}