{
  "name": "Ole",
  "description": "Ecommerce Fashion Platform",
  "categoryId": 14,
  "size": "s",
  "logoFile": "logos/ole_marketplace-logo.webp",
  "websiteUrl": "https://www.oleshop.com/",
  "careersUrl": null,
  "linkedinId": null,
  "linkedinNum": 70880054,
  "crunchbaseId": null,
  "ivcId": null,
  "finderId": "ole",
  "xId": null,
  "facebookId": null,
  "breezyId": null,
  "comeetId": null,
  "greenhouseId": null,
  "leverId": null,
  "addresses": [
    {
      "street": "רבין יצחק",
      "houseNumber": 27,
      "city": "קריית אונו",
      "lat": 32.0647098,
      "lon": 34.8649952
    }
  ],
  "isMultinational": false,
  "isActive": true
}