{
  "name": "Bountica",
  "description": "Pioneering scientific research to develop environmentally safe, nutritious, and naturally produced health solutions.",
  "categoryId": 12,
  "size": "s",
  "logoFile": "logos/bountica-logo.webp",
  "websiteUrl": "https://www.bountica.com/",
  "careersUrl": null,
  "isHiring": false,
  "linkedinId": "bountica",
  "crunchbaseId": "bountica",
  "finderId": "bountica",
  "xId": null,
  "addresses": [
    {
      "street": "הפרדס",
      "houseNumber": 13,
      "city": "תל מונד",
      "lat": 32.2517301,
      "lon": 34.9206075
    }
  ],
  "isMultinational": false,
  "linkedinNum": 74980435
}