{
  "name": "OncoDecipher",
  "description": "OncoDecipher develops a computational biology platform to identify silent mutations and improve pharmaceutical companies’ ability to identify patients that will benefit from the treatment.",
  "categoryId": 12,
  "size": "xs",
  "logoFile": "logos/oncodecipher-logo.webp",
  "websiteUrl": "https://www.oncodecipher.com/",
  "careersUrl": null,
  "linkedinId": null,
  "linkedinNum": null,
  "crunchbaseId": null,
  "ivcId": "A1000000364827",
  "finderId": "oncodecipher",
  "xId": null,
  "facebookId": null,
  "breezyId": null,
  "comeetId": null,
  "greenhouseId": null,
  "leverId": null,
  "addresses": [
    {
      "street": "זרחין אלכסנדר",
      "houseNumber": 13,
      "city": "רעננה",
      "lat": 32.1976788,
      "lon": 34.8811941
    }
  ],
  "isMultinational": false,
  "isActive": true
}