{
  "name": "Buzzer",
  "description": "AI-powered performance optimization for sales and customer support",
  "categoryId": 14,
  "size": "xs",
  "logoFile": "logos/buzzer-logo.webp",
  "websiteUrl": "https://www.buzzer.ai/",
  "careersUrl": null,
  "isHiring": false,
  "linkedinId": null,
  "crunchbaseId": null,
  "finderId": "buzzer",
  "xId": null,
  "addresses": [
    {
      "street": "ברנר",
      "houseNumber": 38,
      "city": "הרצליה",
      "lat": 32.157463,
      "lon": 34.8463645
    }
  ],
  "isMultinational": false,
  "facebookId": "buzzerai",
  "linkedinNum": 74527283
}