{
  "name": "AmplifAIr",
  "description": "Leveraging advanced AI, this company refines customer risk segmentation to optimize pricing discounts.",
  "categoryId": 1,
  "size": "xs",
  "logoFile": "logos/amplifair-logo.webp",
  "websiteUrl": "https://www.amplifair.com/",
  "careersUrl": null,
  "isHiring": false,
  "linkedinId": "amplifair-company",
  "crunchbaseId": null,
  "finderId": "amplifair",
  "xId": null,
  "addresses": [
    {
      "street": "פרנץ קפקא",
      "houseNumber": 4,
      "city": "תל אביב - יפו",
      "lat": 32.127782,
      "lon": 34.834539
    }
  ],
  "isMultinational": false,
  "linkedinNum": 95184012
}