{
  "name": "Tencyle",
  "description": "Securing the supply chain.",
  "categoryId": 7,
  "size": "xs",
  "logoFile": "logos/tencyle-logo.webp",
  "websiteUrl": "https://www.tencyle.com",
  "careersUrl": "https://www.comeet.com/jobs/tencyle/59.00A/fe-engineer/F5.24B",
  "isHiring": true,
  "linkedinId": "tencyle",
  "crunchbaseId": null,
  "finderId": "tencyle",
  "xId": null,
  "addresses": [
    {
      "street": "זבולון המר",
      "houseNumber": 4,
      "city": "ראשון לציון",
      "lat": 31.968866249999998,
      "lon": 34.78207655
    }
  ],
  "isMultinational": false,
  "linkedinNum": 101531964
}