{
  "name": "Hexagate",
  "description": "Rapidly deploy enterprise-grade security to safeguard digital assets and mitigate cyber threats for Web3 applications and asset managers.",
  "categoryId": 7,
  "size": "s",
  "logoFile": "logos/hexagate-logo.webp",
  "websiteUrl": "https://www.hexagate.com/",
  "careersUrl": null,
  "isHiring": false,
  "linkedinId": "gethexagate",
  "crunchbaseId": null,
  "finderId": "hexagate",
  "xId": "hexagate_",
  "addresses": [
    {
      "street": "אלון יגאל",
      "houseNumber": 114,
      "city": "תל אביב - יפו",
      "lat": 32.072746,
      "lon": 34.794968
    }
  ],
  "isMultinational": false,
  "linkedinNum": 86824951
}