{
  "name": "Gigablue",
  "description": "A company leveraging geo-optimized nutrient particles to enhance phytoplankton growth and sequester gigatons of carbon in the ocean for long-term environmental benefits.",
  "categoryId": 17,
  "size": "s",
  "logoFile": "logos/gigablue-logo.webp",
  "websiteUrl": "https://www.gigablue.co/",
  "careersUrl": null,
  "isHiring": false,
  "linkedinId": null,
  "crunchbaseId": null,
  "finderId": "gigablue",
  "xId": null,
  "addresses": [
    {
      "street": null,
      "houseNumber": 16,
      "city": "מנוף",
      "lat": 32.8541336,
      "lon": 35.2367706
    }
  ]
}