{
  "name": "Tweed",
  "description": "Crypto Wallet API for Web3.",
  "categoryId": 10,
  "size": "s",
  "logoFile": "logos/tweed.webp",
  "websiteUrl": "https://paytweed.com/",
  "careersUrl": null,
  "linkedinId": "paytweed",
  "linkedinNum": 91556781,
  "crunchbaseId": null,
  "ivcId": "A1000000419874",
  "finderId": "tweed",
  "xId": null,
  "facebookId": null,
  "breezyId": null,
  "comeetId": null,
  "greenhouseId": null,
  "leverId": null,
  "addresses": [
    {
      "street": "טשרניחובסקי",
      "houseNumber": 24,
      "city": "תל אביב-יפו",
      "lat": 32.074048,
      "lon": 34.7730099
    }
  ],
  "isMultinational": false,
  "isActive": true
}