{
  "name": "MentAI",
  "description": "In-vitro Fertilizations Monitoring Platform",
  "categoryId": 12,
  "size": "xs",
  "logoFile": "logos/mentai.webp",
  "websiteUrl": "https://www.mentai.health/",
  "careersUrl": null,
  "isHiring": false,
  "linkedinId": "mentai-health",
  "linkedinNum": 77015861,
  "crunchbaseId": null,
  "finderId": "mentai",
  "xId": null,
  "facebookId": null,
  "addresses": [
    {
      "street": "אשכול",
      "houseNumber": 117,
      "city": "שקף",
      "lat": 31.514880675920907,
      "lon": 34.93722374230783
    }
  ],
  "isMultinational": false
}
