{
  "name": "Niart",
  "description": "Niart is specializing in smart mobility solutions with a focus on railway automation and safety.",
  "categoryId": 13,
  "size": "s",
  "logoFile": "logos/niart-logo.webp",
  "websiteUrl": "https://niart-systems.com",
  "careersUrl": "https://niart-systems.com/career/",
  "linkedinId": "niart-systems",
  "linkedinNum": 102892214,
  "crunchbaseId": null,
  "ivcId": "A1000000492644",
  "finderId": null,
  "xId": null,
  "facebookId": null,
  "breezyId": null,
  "comeetId": null,
  "greenhouseId": null,
  "leverId": null,
  "addresses": [
    {
      "street": "אופנהיימר",
      "houseNumber": 2,
      "city": "תל אביב-יפו",
      "lat": 32.1185525,
      "lon": 34.8004103
    }
  ],
  "isMultinational": false,
  "isActive": true
}