{
  "name": "LMF Medical",
  "description": "LMF Medical is advancing the field of phototherapy to provide personalized, effective and safe treatments for range of skin conditions.",
  "categoryId": 12,
  "size": "xs",
  "logoFile": "logos/lmf-medical-logo.webp",
  "websiteUrl": "https://lmfmedical.com",
  "careersUrl": null,
  "linkedinId": "lmf-medical",
  "linkedinNum": 101346589,
  "crunchbaseId": null,
  "ivcId": "A1000000485240",
  "finderId": null,
  "xId": null,
  "facebookId": null,
  "breezyId": null,
  "comeetId": null,
  "greenhouseId": null,
  "leverId": null,
  "addresses": [
    {
      "street": null,
      "houseNumber": null,
      "city": "רחובות",
      "lat": 31.8943652,
      "lon": 34.8115292
    }
  ],
  "isMultinational": false,
  "isActive": true
}